Metadata-Version: 2.1
Name: formal-writing-checker
Version: 0.0.4
Summary: Formal Writing Checker
Home-page: https://github.com/MartinoMensio/formal-writing-checker
Author: Martino Mensio
Author-email: martino.mensio@open.ac.uk
License: UNKNOWN
Platform: UNKNOWN
